multiqc_sav/__init__.py
multiqc_sav/multiqc_sav.py
multiqc_sav/modules/__init__.py
multiqc_sav/modules/sav/__init__.py
multiqc_sav/modules/sav/sav.py
multiqc_sav-0.1.0.dist-info/licenses/LICENSE
multiqc_sav-0.1.0.dist-info/METADATA
multiqc_sav-0.1.0.dist-info/WHEEL
multiqc_sav-0.1.0.dist-info/entry_points.txt
multiqc_sav-0.1.0.dist-info/top_level.txt
multiqc_sav-0.1.0.dist-info/RECORD
