Metadata-Version: 2.4
Name: multiqc_sav
Version: 0.1.0
Summary: MultiQC plugin for Illumina SAV InterOp visualizations
Author-email: Matthias De Smet <matthias.desmet@ugent.be>
License: MIT
Project-URL: Homepage, https://github.com/MultiQC/MultiQC_SAV
Project-URL: Repository, https://github.com/MultiQC/MultiQC_SAV
Project-URL: Issues, https://github.com/MultiQC/MultiQC_SAV/issues
Keywords: bioinformatics,illumina,sequencing,multiqc
Classifier: Development Status :: 4 - Beta
Classifier: Environment :: Console
Classifier: Environment :: Web Environment
Classifier: Intended Audience :: Science/Research
Classifier: License :: OSI Approved :: MIT License
Classifier: Natural Language :: English
Classifier: Operating System :: MacOS :: MacOS X
Classifier: Operating System :: POSIX
Classifier: Operating System :: Unix
Classifier: Programming Language :: Python :: 3
Classifier: Programming Language :: Python :: 3.9
Classifier: Programming Language :: Python :: 3.10
Classifier: Programming Language :: Python :: 3.11
Classifier: Programming Language :: Python :: 3.12
Classifier: Programming Language :: Python :: 3.13
Classifier: Topic :: Scientific/Engineering
Classifier: Topic :: Scientific/Engineering :: Bio-Informatics
Classifier: Topic :: Scientific/Engineering :: Visualization
Requires-Python: >=3.9
License-File: LICENSE
Requires-Dist: multiqc>=1.25
Requires-Dist: pandas
Requires-Dist: numpy
Requires-Dist: interop<2,>=1.7.0
Provides-Extra: dev
Requires-Dist: pre-commit; extra == "dev"
Requires-Dist: ruff; extra == "dev"
Requires-Dist: mypy; extra == "dev"
Requires-Dist: pytest; extra == "dev"
Dynamic: license-file
